cdk_preinstalled_amazon_linux_ec2/__init__.py
cdk_preinstalled_amazon_linux_ec2/py.typed
cdk_preinstalled_amazon_linux_ec2/_jsii/__init__.py
cdk_preinstalled_amazon_linux_ec2/_jsii/cdk-preinstalled-amazon-linux-ec2@0.0.13.jsii.tgz
cdk_preinstalled_amazon_linux_ec2-0.0.13.dist-info/LICENSE
cdk_preinstalled_amazon_linux_ec2-0.0.13.dist-info/METADATA
cdk_preinstalled_amazon_linux_ec2-0.0.13.dist-info/WHEEL
cdk_preinstalled_amazon_linux_ec2-0.0.13.dist-info/top_level.txt
cdk_preinstalled_amazon_linux_ec2-0.0.13.dist-info/RECORD
